rtsstat/__init__.py
rtsstat/cli.py
rtsstat-0.1.5.dist-info/LICENSE
rtsstat-0.1.5.dist-info/METADATA
rtsstat-0.1.5.dist-info/WHEEL
rtsstat-0.1.5.dist-info/entry_points.txt
rtsstat-0.1.5.dist-info/top_level.txt
rtsstat-0.1.5.dist-info/RECORD
