Metadata-Version: 2.1
Name: rtsstat
Version: 0.1.5
Summary: rtsstat. A mlf-core based .
Home-page: https://github.com/waseju/rtsstat
Author: Julian Wanner
Author-email: jwgithub@mailbox.org
License: MIT
Keywords: rtsstat
Platform: UNKNOWN
Classifier: Development Status :: 2 - Pre-Alpha
Classifier: Intended Audience :: Developers
Classifier: License :: OSI Approved :: MIT License
Classifier: Natural Language :: English
Classifier: Programming Language :: Python :: 3
Classifier: Programming Language :: Python :: 3.7
Classifier: Programming Language :: Python :: 3.8
Classifier: Programming Language :: Python :: 3.9
Requires-Python: >=3.7
Requires-Dist: rich (==10.15.1)
Requires-Dist: click (==8.0.3)
Requires-Dist: matplotlib (~=3.5.0)
Requires-Dist: numpy (~=1.21.4)
Requires-Dist: pandas (~=1.3.4)
Requires-Dist: seaborn (~=0.11.2)
Requires-Dist: tifffile (~=2021.11.2)
Requires-Dist: statannotations (~=0.4.3)
Requires-Dist: setuptools (~=59.4.0)
